czi_shader/__init__.py
czi_shader/czi_shader.py
czi_shader-0.1.5.dist-info/LICENSE
czi_shader-0.1.5.dist-info/METADATA
czi_shader-0.1.5.dist-info/WHEEL
czi_shader-0.1.5.dist-info/RECORD
