Metadata-Version: 2.1
Name: czi-shader
Version: 0.1.5
Summary: Reproduce the appearance of CZI files (coloring raw data) seen in Zeiss Zen software, and provide channel information extraction of CZI files
Author: zhengmy
Author-email: zhengmy@ion.ac.cn
Requires-Python: >=3.9
Classifier: Programming Language :: Python :: 3
Classifier: Programming Language :: Python :: 3.9
Classifier: Programming Language :: Python :: 3.10
Classifier: Programming Language :: Python :: 3.11
Classifier: Programming Language :: Python :: 3.12
Requires-Dist: aicspylibczi
Requires-Dist: numpy (<2)
Requires-Dist: opencv-python-headless
Requires-Dist: pint (>=0.24,<0.25)
